pfruck_contabo/__init__.py
pfruck_contabo/api_client.py
pfruck_contabo/api_response.py
pfruck_contabo/configuration.py
pfruck_contabo/exceptions.py
pfruck_contabo/model_utils.py
pfruck_contabo/py.typed
pfruck_contabo/rest.py
pfruck_contabo/api/__init__.py
pfruck_contabo/api/images_api.py
pfruck_contabo/api/images_audits_api.py
pfruck_contabo/api/instance_actions_api.py
pfruck_contabo/api/instance_actions_audits_api.py
pfruck_contabo/api/instances_api.py
pfruck_contabo/api/instances_audits_api.py
pfruck_contabo/api/internal_api.py
pfruck_contabo/api/object_storages_api.py
pfruck_contabo/api/object_storages_audits_api.py
pfruck_contabo/api/private_networks_api.py
pfruck_contabo/api/private_networks_audits_api.py
pfruck_contabo/api/roles_api.py
pfruck_contabo/api/roles_audits_api.py
pfruck_contabo/api/secrets_api.py
pfruck_contabo/api/secrets_audits_api.py
pfruck_contabo/api/snapshots_api.py
pfruck_contabo/api/snapshots_audits_api.py
pfruck_contabo/api/tag_assignments_api.py
pfruck_contabo/api/tag_assignments_audits_api.py
pfruck_contabo/api/tags_api.py
pfruck_contabo/api/tags_audits_api.py
pfruck_contabo/api/users_api.py
pfruck_contabo/api/users_audits_api.py
pfruck_contabo/apis/__init__.py
pfruck_contabo/model/__init__.py
pfruck_contabo/model/add_on_quantity_request.py
pfruck_contabo/model/add_on_request.py
pfruck_contabo/model/add_on_response.py
pfruck_contabo/model/additional_ip.py
pfruck_contabo/model/api_permissions_response.py
pfruck_contabo/model/application_config.py
pfruck_contabo/model/application_requirements.py
pfruck_contabo/model/application_requirements_minimum.py
pfruck_contabo/model/application_requirements_optimal.py
pfruck_contabo/model/application_response.py
pfruck_contabo/model/application_response_requirements.py
pfruck_contabo/model/assign_instance_private_network_response.py
pfruck_contabo/model/assign_instance_private_network_response_links.py
pfruck_contabo/model/assigned_tag_response.py
pfruck_contabo/model/assignment_audit_response.py
pfruck_contabo-2.0.0.dist-info/LICENSE
pfruck_contabo-2.0.0.dist-info/METADATA
pfruck_contabo-2.0.0.dist-info/WHEEL
pfruck_contabo-2.0.0.dist-info/top_level.txt
pfruck_contabo-2.0.0.dist-info/RECORD
