Metadata-Version: 2.1
Name: pfruck_contabo
Version: 2.0.0
Summary: This is an UNOFFICIAL Python API client for Contabo
Home-page: https://github.com/p-fruck/python-contabo
Author: OpenAPI Generator community
Author-email: support@contabo.com
Project-URL: Bug Tracker, https://github.com/p-fruck/python-contabo/issues
Keywords: OpenAPI,OpenAPI-Generator,Contabo API
Classifier: Programming Language :: Python :: 3
Classifier: Intended Audience :: Developers
Classifier: License :: OSI Approved :: Apache Software License
Classifier: Operating System :: OS Independent
License-File: LICENSE
Requires-Dist: urllib3 <2.1.0,>=1.25.3
Requires-Dist: python-dateutil
Requires-Dist: pydantic >=2
Requires-Dist: typing-extensions >=4.7.1
